{
  "updated_at": "2025-11-14T02:39:30.373397+00:00",
  "runs": [
    {
      "key": "32d4607eb5",
      "start_utc": "2025-01-03T05:00:00+00:00",
      "end_utc": "2025-01-03T06:00:00+00:00",
      "start_local": "2025-01-03T00:00:00-05:00",
      "end_local": "2025-01-03T01:00:00-05:00",
      "timezone": "America/Toronto",
      "bins": 1,
      "row_count": 11580,
      "note": "",
      "note_updated_at": null
    },
    {
      "key": "288467b398",
      "start_utc": "2025-01-02T05:00:00+00:00",
      "end_utc": "2025-01-02T06:00:00+00:00",
      "start_local": "2025-01-02T00:00:00-05:00",
      "end_local": "2025-01-02T01:00:00-05:00",
      "timezone": "America/Toronto",
      "bins": 1,
      "row_count": 38404,
      "note": "",
      "note_updated_at": null
    },
    {
      "key": "8d91aa5f14",
      "start_utc": "2025-01-01T05:00:00+00:00",
      "end_utc": "2025-01-01T06:00:00+00:00",
      "start_local": "2025-01-01T00:00:00-05:00",
      "end_local": "2025-01-01T01:00:00-05:00",
      "timezone": "America/Toronto",
      "bins": 1,
      "row_count": 16,
      "note": "",
      "note_updated_at": null
    }
  ]
}